[
  {
    "department": "Court Services and Offender Supervision Agency for DC",
    "filename": "dept_court_services_and_offender_supervision_agency_for_dc.json",
    "raw_jobs_filename": "jobs_court_services_and_offender_supervision_agency_for_dc.json",
    "rows": 69,
    "unique_subagencies": 34,
    "total_2024": 113,
    "total_2025": 28,
    "raw_jobs_count": 141
  },
  {
    "department": "Department of Agriculture",
    "filename": "dept_department_of_agriculture.json",
    "raw_jobs_filename": "jobs_department_of_agriculture.json",
    "rows": 3522,
    "unique_subagencies": 2199,
    "total_2024": 7664,
    "total_2025": 1027,
    "raw_jobs_count": 8691
  },
  {
    "department": "Department of Commerce",
    "filename": "dept_department_of_commerce.json",
    "raw_jobs_filename": "jobs_department_of_commerce.json",
    "rows": 1854,
    "unique_subagencies": 1048,
    "total_2024": 3623,
    "total_2025": 255,
    "raw_jobs_count": 3878
  },
  {
    "department": "Department of Defense",
    "filename": "dept_department_of_defense.json",
    "raw_jobs_filename": "jobs_department_of_defense.json",
    "rows": 9651,
    "unique_subagencies": 5316,
    "total_2024": 21487,
    "total_2025": 9977,
    "raw_jobs_count": 31464
  },
  {
    "department": "Department of Education",
    "filename": "dept_department_of_education.json",
    "raw_jobs_filename": "jobs_department_of_education.json",
    "rows": 112,
    "unique_subagencies": 1,
    "total_2024": 424,
    "total_2025": 36,
    "raw_jobs_count": 460
  },
  {
    "department": "Department of Energy",
    "filename": "dept_department_of_energy.json",
    "raw_jobs_filename": "jobs_department_of_energy.json",
    "rows": 1151,
    "unique_subagencies": 609,
    "total_2024": 2448,
    "total_2025": 226,
    "raw_jobs_count": 2674
  },
  {
    "department": "Department of Health and Human Services",
    "filename": "dept_department_of_health_and_human_services.json",
    "raw_jobs_filename": "jobs_department_of_health_and_human_services.json",
    "rows": 5004,
    "unique_subagencies": 2911,
    "total_2024": 8441,
    "total_2025": 1191,
    "raw_jobs_count": 9632
  },
  {
    "department": "Department of Homeland Security",
    "filename": "dept_department_of_homeland_security.json",
    "raw_jobs_filename": "jobs_department_of_homeland_security.json",
    "rows": 6798,
    "unique_subagencies": 3653,
    "total_2024": 14066,
    "total_2025": 6639,
    "raw_jobs_count": 20705
  },
  {
    "department": "Department of Housing and Urban Development",
    "filename": "dept_department_of_housing_and_urban_development.json",
    "raw_jobs_filename": "jobs_department_of_housing_and_urban_development.json",
    "rows": 173,
    "unique_subagencies": 1,
    "total_2024": 1289,
    "total_2025": 30,
    "raw_jobs_count": 1319
  },
  {
    "department": "Department of Justice",
    "filename": "dept_department_of_justice.json",
    "raw_jobs_filename": "jobs_department_of_justice.json",
    "rows": 2385,
    "unique_subagencies": 961,
    "total_2024": 8174,
    "total_2025": 4859,
    "raw_jobs_count": 13033
  },
  {
    "department": "Department of Labor",
    "filename": "dept_department_of_labor.json",
    "raw_jobs_filename": "jobs_department_of_labor.json",
    "rows": 494,
    "unique_subagencies": 276,
    "total_2024": 1260,
    "total_2025": 65,
    "raw_jobs_count": 1325
  },
  {
    "department": "Department of State",
    "filename": "dept_department_of_state.json",
    "raw_jobs_filename": "jobs_department_of_state.json",
    "rows": 181,
    "unique_subagencies": 3,
    "total_2024": 1337,
    "total_2025": 185,
    "raw_jobs_count": 1522
  },
  {
    "department": "Department of Transportation",
    "filename": "dept_department_of_transportation.json",
    "raw_jobs_filename": "jobs_department_of_transportation.json",
    "rows": 4012,
    "unique_subagencies": 2969,
    "total_2024": 4976,
    "total_2025": 2163,
    "raw_jobs_count": 7139
  },
  {
    "department": "Department of Veterans Affairs",
    "filename": "dept_department_of_veterans_affairs.json",
    "raw_jobs_filename": "jobs_department_of_veterans_affairs.json",
    "rows": 19121,
    "unique_subagencies": 8063,
    "total_2024": 38530,
    "total_2025": 37942,
    "raw_jobs_count": 76472
  },
  {
    "department": "Department of the Air Force",
    "filename": "dept_department_of_the_air_force.json",
    "raw_jobs_filename": "jobs_department_of_the_air_force.json",
    "rows": 12845,
    "unique_subagencies": 4746,
    "total_2024": 27100,
    "total_2025": 11079,
    "raw_jobs_count": 38179
  },
  {
    "department": "Department of the Army",
    "filename": "dept_department_of_the_army.json",
    "raw_jobs_filename": "jobs_department_of_the_army.json",
    "rows": 29531,
    "unique_subagencies": 16504,
    "total_2024": 42847,
    "total_2025": 12164,
    "raw_jobs_count": 55011
  },
  {
    "department": "Department of the Interior",
    "filename": "dept_department_of_the_interior.json",
    "raw_jobs_filename": "jobs_department_of_the_interior.json",
    "rows": 6247,
    "unique_subagencies": 2730,
    "total_2024": 10941,
    "total_2025": 1964,
    "raw_jobs_count": 12905
  },
  {
    "department": "Department of the Navy",
    "filename": "dept_department_of_the_navy.json",
    "raw_jobs_filename": "jobs_department_of_the_navy.json",
    "rows": 11207,
    "unique_subagencies": 3311,
    "total_2024": 28276,
    "total_2025": 14530,
    "raw_jobs_count": 42806
  },
  {
    "department": "Department of the Treasury",
    "filename": "dept_department_of_the_treasury.json",
    "raw_jobs_filename": "jobs_department_of_the_treasury.json",
    "rows": 811,
    "unique_subagencies": 196,
    "total_2024": 7776,
    "total_2025": 218,
    "raw_jobs_count": 7994
  },
  {
    "department": "Executive Office of the President",
    "filename": "dept_executive_office_of_the_president.json",
    "raw_jobs_filename": "jobs_executive_office_of_the_president.json",
    "rows": 133,
    "unique_subagencies": 63,
    "total_2024": 142,
    "total_2025": 86,
    "raw_jobs_count": 228
  },
  {
    "department": "General Services Administration",
    "filename": "dept_general_services_administration.json",
    "raw_jobs_filename": "jobs_general_services_administration.json",
    "rows": 163,
    "unique_subagencies": 1,
    "total_2024": 1291,
    "total_2025": 15,
    "raw_jobs_count": 1306
  },
  {
    "department": "Judicial Branch",
    "filename": "dept_judicial_branch.json",
    "raw_jobs_filename": "jobs_judicial_branch.json",
    "rows": 509,
    "unique_subagencies": 239,
    "total_2024": 513,
    "total_2025": 342,
    "raw_jobs_count": 855
  },
  {
    "department": "Legislative Branch",
    "filename": "dept_legislative_branch.json",
    "raw_jobs_filename": "jobs_legislative_branch.json",
    "rows": 884,
    "unique_subagencies": 239,
    "total_2024": 1377,
    "total_2025": 1069,
    "raw_jobs_count": 2446
  },
  {
    "department": "National Aeronautics and Space Administration",
    "filename": "dept_national_aeronautics_and_space_administration.json",
    "raw_jobs_filename": "jobs_national_aeronautics_and_space_administration.json",
    "rows": 337,
    "unique_subagencies": 7,
    "total_2024": 1181,
    "total_2025": 188,
    "raw_jobs_count": 1369
  },
  {
    "department": "National Foundation on the Arts and the Humanities",
    "filename": "dept_national_foundation_on_the_arts_and_the_humanities.json",
    "raw_jobs_filename": "jobs_national_foundation_on_the_arts_and_the_humanities.json",
    "rows": 43,
    "unique_subagencies": 18,
    "total_2024": 78,
    "total_2025": 3,
    "raw_jobs_count": 81
  },
  {
    "department": "Other Agencies and Independent Organizations",
    "filename": "dept_other_agencies_and_independent_organizations.json",
    "raw_jobs_filename": "jobs_other_agencies_and_independent_organizations.json",
    "rows": 4062,
    "unique_subagencies": 1658,
    "total_2024": 12256,
    "total_2025": 1405,
    "raw_jobs_count": 13661
  },
  {
    "department": "Unknown",
    "filename": "dept_unknown.json",
    "raw_jobs_filename": "jobs_unknown.json",
    "rows": 1,
    "unique_subagencies": 1,
    "total_2024": 0,
    "total_2025": 1,
    "raw_jobs_count": 1
  }
]